gptzzzs/__init__.py
gptzzzs/normal_change.py
gptzzzs/data/adjectives.json
gptzzzs/data/common_words.json
gptzzzs/data/finnlp-separate.json
gptzzzs/data/finnlp-together.json
gptzzzs/data/zaibacu.json
gptzzzs-0.0.1.dist-info/METADATA
gptzzzs-0.0.1.dist-info/WHEEL
gptzzzs-0.0.1.dist-info/top_level.txt
gptzzzs-0.0.1.dist-info/RECORD
