Metadata-Version: 2.1
Name: gptzzzs
Version: 0.0.1
Summary: Gptzzzs is a tool that attempts large language model detection evasion by changing grammar.
Home-page: https://github.com/Declipsonator/GPTZzzs
Author: Jackson Hickey
Author-email: jackson@jacksonhickey.tech
Classifier: Programming Language :: Python :: 3.1
Classifier: License :: OSI Approved :: GNU General Public License v3 (GPLv3)
Classifier: Operating System :: OS Independent
Requires-Python: >=3.1
